debug_cmd/__init__.py
debug_cmd/debug_cmd.py
debug_cmd-1.0.4.dist-info/LICENSE
debug_cmd-1.0.4.dist-info/METADATA
debug_cmd-1.0.4.dist-info/WHEEL
debug_cmd-1.0.4.dist-info/entry_points.txt
debug_cmd-1.0.4.dist-info/top_level.txt
debug_cmd-1.0.4.dist-info/RECORD
