Metadata-Version: 2.1
Name: debug-cmd
Version: 1.0.4
Summary: Debug linux command error by using GPT/LLM.
Home-page: https://github.com/megmogmog1965/debug_cmd
Author: Yusuke Kawatsu
Author-email: mail@sample.com
License: MIT
Keywords: gpt debug
Classifier: License :: OSI Approved :: MIT License
Classifier: Programming Language :: Python :: 3.10
Requires-Python: >=3
License-File: LICENSE
Requires-Dist: openai
Requires-Dist: langchain
